{"article_info":{"category_id":2,"category_name":"勘違い敬語","file_name":"宜しくお願い致します","list_title":"「宜しくお願い致します」は間違い？","page_title":"「宜しくお願い致します」は間違い？勘違いマナーについて","date":"2022-02-03","url":"https://xn--gdvx14f.jp/%E5%AE%9C%E3%81%97%E3%81%8F%E3%81%8A%E9%A1%98%E3%81%84%E8%87%B4%E3%81%97%E3%81%BE%E3%81%99/","url_no_percent_encode":"https://敬語.jp/宜しくお願い致します/"},"items":[{"text":"「宜しくお願い致します」は間違い？勘違いマナーについて","type":"h1"},{"text_items":[{"styles":[],"text":"「","url":null},{"styles":["strong"],"text":"宜しくお願い致します","url":null},{"styles":[],"text":"」は正しい敬語です。\nしかし、「間違った書き方なので失礼だ」と勘違いしている人もいます。","url":null}],"type":"body"},{"text_items":[{"styles":[],"text":"企業からのメールで使われ方を確認","url":null}],"type":"h2"},{"text_items":[{"styles":[],"text":"皆さんのスマートフォンやパソコンのメールボックスで検索していただくと、大きな企業の自動返信などで来るメールには、\n「","url":null},{"styles":["strong"],"text":"よろしくお願いいたします","url":null},{"styles":[],"text":"」か「","url":null},{"styles":["strong"],"text":"よろしくお願い申し上げます","url":null},{"styles":[],"text":"」と記述されている場合がほとんどだと思います。","url":null},{"styles":[],"text":"\n\n","url":null},{"styles":[],"text":"これには、","url":null}],"type":"body"},{"list_items":[[{"styles":["strong"],"text":"「宜しく」は常用漢字として書けない","url":null}],[{"styles":["strong"],"text":"「お願い致します」は公用文では推奨されていない書き方","url":null}]],"type":"num_list"},{"text_items":[{"styles":[],"text":"という二つの理由があります。","url":null}],"type":"body"},{"text_items":[{"styles":[],"text":"「宜しく」は常用漢字として書けない","url":null}],"type":"h2"},{"url":"/img/hxfhjg5e46.webp","type":"img"},{"text_items":[{"styles":[],"text":"常用漢字表において、「宜」は「ぎ」という読み方しかなく、「よろ」という読み方は書かれていません","url":null},{"styles":["ref_num"],"text":"1","url":"#fn:1"},{"styles":[],"text":"。\nそのため、常用漢字表の範囲内では「宜しく」とは書けません。","url":null},{"styles":[],"text":"\n\n","url":null},{"styles":[],"text":"この常用漢字表は、文化庁が出した「一般の社会生活における漢字使用の目安","url":null},{"styles":["ref_num"],"text":"2","url":"#fn:2"},{"styles":[],"text":"」なので、新聞やニュース、企業がお客様に向けて自動で送るメールのような、様々な人が読む文章において重視されています。","url":null},{"styles":[],"text":"\n\n","url":null},{"styles":[],"text":"しかし、ほとんどの人が読めないような難しい漢字であれば分かりますが、「宜しく」は大人にとって読むことの難しい書き方ではなく、失礼と言うのは大げさです。","url":null}],"type":"body"},{"text_items":[{"styles":[],"text":"「宜しく」は当て字？","url":null}],"type":"h2"},{"url":"/img/434agkd2rf.webp","type":"img"},{"text_items":[{"styles":[],"text":"「宜しく　当て字」でWeb検索をすると、\n「","url":null},{"styles":["strong"],"text":"宜には「よろ」という読み方はなく、宜しくは当て字","url":null},{"styles":[],"text":"」\nという説明をしている記事がいくつか見つかります。","url":null},{"styles":[],"text":"\n\n","url":null},{"styles":[],"text":"これに関しては誤りで、例えば漢文の教科書には「宜」という漢字は「宜しく〜すべし」の形で訓読すると書かれています","url":null},{"styles":["ref_num"],"text":"3","url":"#fn:3"},{"styles":[],"text":"。","url":null},{"styles":[],"text":"\n\n","url":null},{"styles":[],"text":"また、その言葉が当て字かどうかは辞書に載っています。\n特に広辞苑はその記載が多く、例えば、「流石（さすが）」「野暮（やぼ）」「兎に角（とにかく）」には「当て字」であるとの説明があります。\nしかし、「宜しく」にはありません","url":null},{"styles":["ref_num"],"text":"4","url":"#fn:4"},{"styles":[],"text":"。","url":null},{"styles":[],"text":"\n\n","url":null},{"styles":[],"text":"宜敷（よろしく）という、坂本龍馬も手紙で使用している","url":null},{"styles":["ref_num"],"text":"5","url":"#fn:5"},{"styles":[],"text":"古い書き方があり、この「敷」の方が当て字という話と混同しているようです","url":null},{"styles":["ref_num"],"text":"6","url":"#fn:6"},{"styles":[],"text":"。","url":null}],"type":"body"},{"text_items":[{"styles":[],"text":"「お願い致します」は公用文では推奨されていない書き方","url":null}],"type":"h2"},{"text_items":[{"styles":[],"text":"公用文の書き方を統一しようと、文化庁が「公用文作成の考え方（建議）","url":null},{"styles":["ref_num"],"text":"7","url":"#fn:7"},{"styles":[],"text":"」という資料を作り、誰にでも見ることが出来る形で公開しています。","url":null},{"styles":[],"text":"\n\n","url":null},{"styles":[],"text":"その中に「","url":null},{"styles":["strong"],"text":"動詞・形容詞などの補助的な用法","url":null},{"styles":[],"text":"」","url":null},{"styles":["strong"],"text":"はひらがなで書く","url":null},{"styles":[],"text":"という決まりがあります","url":null},{"styles":["ref_num"],"text":"8","url":"#fn:8"},{"styles":[],"text":"。\nこれは、例えば「〜して行く」を「〜していく」に、「〜して頂く」を「〜していただく」とするように、他の動詞や形容詞に付ける補助的な語はひらがなに統一するというものです。\n「","url":null},{"styles":["strong"],"text":"お願い致します","url":null},{"styles":[],"text":"」の場合は「","url":null},{"styles":["strong"],"text":"願う","url":null},{"styles":[],"text":"」という動詞に「","url":null},{"styles":["strong"],"text":"する","url":null},{"styles":[],"text":"」の","url":null},{"styles":["humble"],"text":"謙譲語","url":null},{"styles":[],"text":"である「","url":null},{"styles":["strong"],"text":"致す","url":null},{"styles":[],"text":"」という補助的な動詞がついています。\nなので公用文では「","url":null},{"styles":["strong"],"text":"お願いいたします","url":null},{"styles":[],"text":"」と書きます。","url":null},{"styles":[],"text":"\n\n","url":null},{"styles":[],"text":"企業がこの規則に従う必要は無いのですが、「公用文作成の考え方（建議）」は読みやすさ、勘違いのされにくさを重視して作られています","url":null},{"styles":["ref_num"],"text":"9","url":"#fn:9"},{"styles":[],"text":"。\nなので、「よろしくお願いいたします」の書き方を統一するための分かりやすい指標として選ばれやすいです。","url":null}],"type":"body"},{"text_items":[{"styles":[],"text":"「致します」に否定的な意味は無い","url":null}],"type":"h2"},{"url":"/img/scu3ew97ua.webp","type":"img"},{"text_items":[{"styles":[],"text":"「致す」という言葉は、少なくとも二つの辞書に否定的な意味があると載っています","url":null},{"styles":["ref_num"],"text":"10","url":"#fn:10"},{"styles":[],"text":"。","url":null}],"type":"body"},{"text_items":[{"styles":[],"text":"そのことがもとで、ある結果、特によくない結果を引き起こす。ある状態に立ち至らせる。\n「私の不明の致すところ」","url":null}],"type":"block_quote"},{"text_items":[{"styles":[],"text":"あることが原因となってよくない結果を引き起こす。\n「これは私の不徳の致すところです」","url":null}],"type":"block_quote"},{"text_items":[{"styles":[],"text":"これらの記載を理由に、「お願い致します」は失礼な書き方だと解説している記事がたくさんあります。","url":null},{"styles":[],"text":"\n\n","url":null},{"styles":[],"text":"しかし、これは「不徳の致すところ」や「無知の致すところ」のように、\n","url":null},{"styles":["strong"],"text":"「引き起こした原因」 + の致すところ","url":null},{"styles":[],"text":"と書かないと当てはまりません。\n先ほど引用した辞書の用例には「〜の致すところ」という形式のものしかありません。","url":null},{"styles":[],"text":"\n\n","url":null},{"styles":[],"text":"明鏡国語辞典には「〜の致すところ」という形式で用いると明記されています","url":null},{"styles":["ref_num"],"text":"11","url":"#fn:11"},{"styles":[],"text":"。","url":null}],"type":"body"},{"text_items":[{"styles":[],"text":"《「…の致すところ」の形で》それが原因となって、ある（よくない）結果を引き起こす。もたらす。招く。","url":null}],"type":"block_quote"},{"text_items":[{"styles":[],"text":"ですから、「〜の致すところ」には否定的な意味がありますが、「致します」にはありません。","url":null},{"styles":[],"text":"\n\n","url":null},{"styles":[],"text":"平安時代では、「致す」は現代語には無い「結果としてもたらす。ひきおこす」の意味でも用いられていました","url":null},{"styles":["ref_num"],"text":"12","url":"#fn:12"},{"styles":[],"text":"。\n現代では唯一「〜の致すところ」の形でのみ残ったのだと考えられます。","url":null},{"styles":[],"text":"\n\n","url":null},{"styles":[],"text":"「お願い致します」における「致す」は、単に「する」の","url":null},{"styles":["humble"],"text":"謙譲語","url":null},{"styles":[],"text":"ですし、\n「致す」には「","url":null},{"styles":["strong"],"text":"心を尽くす","url":null},{"styles":[],"text":"」や「","url":null},{"styles":["strong"],"text":"全力で事を行う","url":null},{"styles":[],"text":"」など肯定的な意味も載っています","url":null},{"styles":["ref_num"],"text":"10","url":"#fn:10"},{"styles":[],"text":"。","url":null},{"styles":[],"text":"\n\n","url":null},{"styles":[],"text":"なので、「いたします」とひらがなで書く理由は「","url":null},{"styles":["strong"],"text":"公用文で推奨されている書き方だから","url":null},{"styles":[],"text":"」以外ありません。","url":null}],"type":"body"},{"text_items":[{"styles":[],"text":"公用文でも「致す」を用いても良い書き方","url":null}],"type":"h2"},{"text_items":[{"styles":[],"text":"公用文作成の規則では、補助的な動詞以外であれば漢字の「致す」でも構いません。\nなので「〜を致します」や「〜に致します」といった書き方は問題ありません。","url":null}],"type":"body"},{"list_items":[[{"styles":["strong"],"text":"ご送付を致します","url":null}],[{"styles":["strong"],"text":"ご案内を致します","url":null}],[{"styles":["strong"],"text":"尽力を致します","url":null}],[{"styles":["strong"],"text":"こちらからお話を致します","url":null}],[{"styles":["strong"],"text":"そのように致します","url":null}]],"type":"bullet_list"},{"text_items":[{"styles":[],"text":"いつから失礼と言われるようになったのか","url":null}],"type":"h2"},{"text_items":[{"styles":[],"text":"Google検索にはページの最終更新日を絞って検索する機能があり、それにより「宜しくお願い致します」が失礼と呼ばれるようになった時期を特定することが可能です。","url":null},{"styles":[],"text":"\n\n","url":null},{"styles":[],"text":"最終更新日が2022年より前、2021年より前、…と順番に調べてみると、2016年の1月に公開されたブログの記事が最も古く、それ以前には「失礼」という説明が書かれている記事が一件も見つからないことが分かります。","url":null},{"styles":[],"text":"\n\n","url":null},{"styles":[],"text":"「日常的に良く見かける『宜しくお願い致します』という書き方は、実は間違いであり失礼だった」という嘘のマナーは意外性があり注目を集めやすかったためか、2017年を中心に大量のブログ記事が書かれるようになり、現在では「宜しくお願い致します」と検索すると同様の説明の記事が大量に並ぶほどになっています。","url":null}],"type":"body"},{"text_items":[{"styles":[],"text":"まとめ","url":null}],"type":"h2"},{"text_items":[{"styles":[],"text":"「","url":null},{"styles":["strong"],"text":"宜しくお願い致します","url":null},{"styles":[],"text":"」","url":null},{"styles":["strong"],"text":"は失礼","url":null},{"styles":[],"text":"というマナーは、誰かの勘違いによって生まれた、いわゆる嘘マナーです。","url":null},{"styles":[],"text":"\n\n","url":null},{"styles":[],"text":"全く失礼ではなく、昔から使われている正しい敬語です。","url":null},{"styles":[],"text":"\n\n","url":null},{"styles":[],"text":"しかし、どれほどの人が勘違いをしているのかは分かりませんが、\n「宜しくお願い致します」でWeb検索をすると、失礼だと説明している記事が数多く見つかります。","url":null},{"styles":[],"text":"\n\n","url":null},{"styles":[],"text":"ですから、現状では、特にこだわりがなく、会社や上司からの指示もなければ、\n「","url":null},{"styles":["strong"],"text":"よろしくお願いいたします","url":null},{"styles":[],"text":"」と書いた方が無難だと思います。","url":null},{"styles":[],"text":"\n\n","url":null},{"styles":[],"text":"とはいえ、「","url":null},{"styles":["strong"],"text":"宜しくお願い致します","url":null},{"styles":[],"text":"」と書く人も多いですし、\nこちらの方が「","url":null},{"styles":["strong"],"text":"堅実な印象がある","url":null},{"styles":[],"text":"」などの理由で使用している人もいますから、利点・欠点を踏まえた上で決めることが一番です。","url":null},{"styles":[],"text":"\n\n","url":null},{"styles":[],"text":"メールの場合、先方の書き方に合わせるという方法もあります。","url":null}],"type":"body"}],"references":[{"list_items":[[{"styles":["link"],"text":"常用漢字表","url":"https://www.bunka.go.jp/kokugo_nihongo/sisaku/joho/joho/kijun/naikaku/pdf/joyokanjihyo_20101130.pdf"},{"styles":[],"text":" 文化庁","url":null}],[{"styles":["link"],"text":"常用漢字表","url":"https://www.bunka.go.jp/kokugo_nihongo/sisaku/joho/joho/kijun/naikaku/pdf/joyokanjihyo_20101130.pdf"},{"styles":[],"text":" 文化庁, p1\n原文は「一般の社会生活において，現代の国語を書き表す場合の漢字使用の目安」ですが、文脈に合わせて省略しています。","url":null}],[{"styles":["link"],"text":"高校初級漢文","url":"https://www.amazon.co.jp/dp/4578012476/ref=nosim?tag=zoome0a9-22"},{"styles":[],"text":" 文英堂, p16-17","url":null}],[{"styles":[],"text":"広辞苑 第七版 【さすが】【野暮】【とにかく】【宜しく】の項\n「宜しく」に関しては、デジタル大辞泉 ver.3.2.0 、スーパー大辞林 3.0、明鏡国語辞典 第三版でも「当て字」だという説明の無いことを確認","url":null}],[{"styles":["link"],"text":"安政三年九月二十九日　相良屋源之助あて","url":"https://www.aozora.gr.jp/cards/000908/card51382.html"},{"styles":[],"text":" 坂本龍馬","url":null}],[{"styles":["link"],"text":"「よろしく」を「宜敷く」と書くのは間違いですか？","url":"https://kanjibunka.com/kanji-faq/old-faq/q0328/"},{"styles":[],"text":" 漢字文化資料館","url":null}],[{"styles":["link"],"text":"公用文作成の考え方（建議）","url":"https://www.bunka.go.jp/seisaku/bunkashingikai/kokugo/hokoku/pdf/93651301_01.pdf"},{"styles":[],"text":" 文化庁","url":null}],[{"styles":["link"],"text":"公用文作成の考え方（建議）","url":"https://www.bunka.go.jp/seisaku/bunkashingikai/kokugo/hokoku/pdf/93651301_01.pdf"},{"styles":[],"text":" 文化庁, p11\n調べた限り最も古いものでは、1952年に政府が各省庁に通達した「公用文作成の要領」に類似の規則があります。\n","url":null},{"styles":["link"],"text":"公用文作成の要領","url":"https://www.bunka.go.jp/kokugo_nihongo/sisaku/joho/joho/series/21/pdf/kokugo_series_021_02.pdf"},{"styles":[],"text":" p7","url":null}],[{"styles":[],"text":"「公用文作成の考え方（建議）」の全ての規則が読みやすさを重視しているわけではありません。\n大きな数は三桁区切りにする（11,000円よりも1万1000円の方が読みやすいですよね）、敬語の「ございます」は使わないなど、企業が採用すべきではない規則もあります。","url":null}],[{"styles":[],"text":"デジタル大辞泉 ver.3.2.0 、スーパー大辞林 3.0 【致す】の項","url":null}],[{"styles":[],"text":"明鏡国語辞典 第三版 【致す】の項","url":null}],[{"styles":[],"text":"広辞苑 第七版 【致す】の項\nいつから「結果としてもたらす。ひきおこす。」の意味で使われなくなったのかは未確認です。","url":null}]],"type":"num_list"}],"ad_positions":[1,22]}